hash_artifacts/__init__.py
hash_artifacts/hash_artifacts.py
hash_artifacts-0.0.1.dist-info/METADATA
hash_artifacts-0.0.1.dist-info/WHEEL
hash_artifacts-0.0.1.dist-info/entry_points.txt
hash_artifacts-0.0.1.dist-info/top_level.txt
hash_artifacts-0.0.1.dist-info/RECORD
